annex_remote_internxt/__init__.py
annex_remote_internxt/_version.py
annex_remote_internxt/git.py
annex_remote_internxt/internxt_cli.py
annex_remote_internxt/internxt_drive.py
annex_remote_internxt/remote.py
annex_remote_internxt/tests/__init__.py
annex_remote_internxt/tests/fixtures.py
annex_remote_internxt/tests/test_drive.py
annex_remote_internxt/tests/test_fixtures.py
annex_remote_internxt/tests/test_internxtcli.py
annex_remote_internxt/tests/test_remote.py
git_annex_remote_internxt-0.1.5.dist-info/METADATA
git_annex_remote_internxt-0.1.5.dist-info/WHEEL
git_annex_remote_internxt-0.1.5.dist-info/entry_points.txt
git_annex_remote_internxt-0.1.5.dist-info/licenses/LICENSE
git_annex_remote_internxt-0.1.5.dist-info/RECORD
