Metadata-Version: 2.4
Name: git-annex-remote-internxt
Version: 0.1.5
Summary: git annex remote internxt
Project-URL: Homepage, https://hub.datalad.org/git-annex/git-annex-remote-internxt
Project-URL: Documentation, https://hub.datalad.org/git-annex/git-annex-remote-internxt#readme
Project-URL: Issues, https://hub.datalad.org/git-annex/git-annex-remote-internxt/issues
Project-URL: Source, https://hub.datalad.org/git-annex/git-annex-remote-internxt
Project-URL: Changelog, https://hub.datalad.org/git-annex/git-annex-remote-internxt/src/branch/main/CHANGELOG.md
Author-email: "Adina S. Wagner" <adina@ngln.eu>, Michael Hanke <mih@ngln.eu>
Maintainer-email: "Adina S. Wagner" <adina@ngln.eu>, Michael Hanke <mih@ngln.eu>
License-Expression: MIT
License-File: LICENSE
Keywords: git,git-annex,internxt,special-remote
Classifier: Development Status :: 4 - Beta
Classifier: Intended Audience :: Developers
Classifier: Intended Audience :: End Users/Desktop
Classifier: License :: OSI Approved :: MIT License
Classifier: Natural Language :: English
Classifier: Operating System :: OS Independent
Classifier: Programming Language :: Python
Classifier: Programming Language :: Python :: 3
Classifier: Programming Language :: Python :: 3.10
Classifier: Programming Language :: Python :: 3.11
Classifier: Programming Language :: Python :: 3.12
Classifier: Programming Language :: Python :: 3.13
Classifier: Programming Language :: Python :: Implementation :: CPython
Classifier: Programming Language :: Python :: Implementation :: PyPy
Classifier: Topic :: Software Development
Classifier: Topic :: Software Development :: Version Control
Classifier: Topic :: Software Development :: Version Control :: Git
Requires-Python: >=3.10
Requires-Dist: annexremote
